flask_beautiful_messages
