Metadata-Version: 1.1
Name: flask-beautiful-messages
Version: 1.2.8
Summary: This library allows Flask developers to quickly create beautiful email and webpage templates
Home-page: https://github.com/sudouser2010/flask_beautiful_messages
Author: Herbert Dawkins
Author-email: DrDawkins@ClearScienceInc.com
License: UNKNOWN
Download-URL: https://github.com/sudouser2010/flask_beautiful_messages/archive/1.2.8.tar.gz
Keywords: flask,beautiful,messages,email,webpage,template
Platform: UNKNOWN
